sadtalker/__init__.py
sadtalker/aiy.py
sadtalker/generate_batch.py
sadtalker/generate_facerender_batch.py
sadtalker/gradio_demo.py
sadtalker/test_audio2coeff.py
sadtalker/audio2exp_models/__init__.py
sadtalker/audio2exp_models/audio2exp.py
sadtalker/audio2exp_models/networks.py
sadtalker/audio2pose_models/__init__.py
sadtalker/audio2pose_models/audio2pose.py
sadtalker/audio2pose_models/audio_encoder.py
sadtalker/audio2pose_models/cvae.py
sadtalker/audio2pose_models/discriminator.py
sadtalker/audio2pose_models/networks.py
sadtalker/audio2pose_models/res_unet.py
sadtalker/face3d/__init__.py
sadtalker/face3d/extract_kp_videos.py
sadtalker/face3d/extract_kp_videos_safe.py
sadtalker/face3d/visualize.py
sadtalker/face3d/data/__init__.py
sadtalker/face3d/data/base_dataset.py
sadtalker/face3d/data/flist_dataset.py
sadtalker/face3d/data/image_folder.py
sadtalker/face3d/data/template_dataset.py
sadtalker/face3d/models/__init__.py
sadtalker/face3d/models/base_model.py
sadtalker/face3d/models/bfm.py
sadtalker/face3d/models/facerecon_model.py
sadtalker/face3d/models/losses.py
sadtalker/face3d/models/networks.py
sadtalker/face3d/models/template_model.py
sadtalker/face3d/models/arcface_torch/__init__.py
sadtalker/face3d/models/arcface_torch/dataset.py
sadtalker/face3d/models/arcface_torch/eval_ijbc.py
sadtalker/face3d/models/arcface_torch/inference.py
sadtalker/face3d/models/arcface_torch/losses.py
sadtalker/face3d/models/arcface_torch/onnx_helper.py
sadtalker/face3d/models/arcface_torch/onnx_ijbc.py
sadtalker/face3d/models/arcface_torch/partial_fc.py
sadtalker/face3d/models/arcface_torch/torch2onnx.py
sadtalker/face3d/models/arcface_torch/train.py
sadtalker/face3d/models/arcface_torch/backbones/__init__.py
sadtalker/face3d/models/arcface_torch/backbones/iresnet.py
sadtalker/face3d/models/arcface_torch/backbones/iresnet2060.py
sadtalker/face3d/models/arcface_torch/backbones/mobilefacenet.py
sadtalker/face3d/models/arcface_torch/configs/3millions.py
sadtalker_z-0.1.6.dist-info/LICENSE
sadtalker_z-0.1.6.dist-info/METADATA
sadtalker_z-0.1.6.dist-info/WHEEL
sadtalker_z-0.1.6.dist-info/top_level.txt
sadtalker_z-0.1.6.dist-info/RECORD
