Metadata-Version: 2.1
Name: sadtalker-z
Version: 0.1.6
Summary: sadtalker
License-File: LICENSE
Requires-Dist: numpy ==1.23.4
Requires-Dist: face-alignment >=1.3.5
Requires-Dist: imageio >=2.19.3
Requires-Dist: imageio-ffmpeg >=0.4.7
Requires-Dist: librosa >=0.9.2
Requires-Dist: numba
Requires-Dist: resampy >=0.3.1
Requires-Dist: pydub >=0.25.1
Requires-Dist: scipy >=1.10.1
Requires-Dist: kornia >=0.6.8
Requires-Dist: tqdm
Requires-Dist: yacs >=0.1.8
Requires-Dist: pyyaml
Requires-Dist: joblib >=1.1.0
Requires-Dist: scikit-image >=0.19.3
Requires-Dist: basicsr >=1.4.2
Requires-Dist: facexlib >=0.3.0
Requires-Dist: gradio
Requires-Dist: gfpgan
Requires-Dist: av
Requires-Dist: safetensors
Requires-Dist: pyaiy
Requires-Dist: opencv-python
